Workbook

Sheet Cover
B2: [ORGANIZATION NAME]
B3: 09 — Project Budget
B4: [Project Name]
B6: DOCUMENT CONTROL | E6: PMBOK® 8 ALIGNMENT
B7: Project name | C7: [Project Name] | E7: Performance domain(s) | F7: Finance
B8: Project ID | C8: PRJ-2026-001 | E8: Focus area(s) | F8: Planning, Monitoring & Controlling
B9: Document ID | C9: PRJ-2026-001-BUD | E9: Toolkit | F9: PMI Predictive Project Management Toolkit
B10: Document title | C10: Project Budget | E10: Standard | F10: Aligned to the PMBOK® Guide – Eighth Edition
B11: Version | C11: 0.1
B12: Status | C12: Draft
B13: Date | C13: 2026-10-27
B14: Project Sponsor | C14: [Project Sponsor]
B15: Project Manager / Owner | C15: [Project Manager]
B16: Approver | C16: Sponsor
B17: Classification | C17: Internal
B18: Currency | C18: CAD
B19: File location | C19: [SharePoint / repository path]
B22: REVISION HISTORY
B23: Version | C23: Date | D23: Author | E23: Description of change | F23: CR ref. | G23: Approved by
B24: 0.1 | C24: 2026-10-27 | D24: [Project Manager] | E24: Initial draft created from toolkit template | F24: N/A
B30: VERSIONING SCHEME
B31: 0.1 - 0.9 | C31: Draft | D31: Work in progress. Increment the minor digit for each review cycle (0.1, 0.2 ...).
B32: 1.0 | C32: Approved / Baselined | D32: First version formally approved by the designated approver. Becomes the baseline.
B33: 1.1, 1.2 ... | C33: Minor revision | D33: Editorial or clarifying change with NO impact on scope, schedule or cost baselines. PM approval.
B34: 2.0, 3.0 ... | C34: Major revision | D34: Change that alters a baseline. Requires an approved Change Request (doc 20) logged in the Change Log (doc 21).
B36: HOW TO USE THIS WORKBOOK
B37: 1. Set labour rates and reserve percentages on the Assumptions sheet (amber cells).
B38: 2. Build the bottom-up estimate on the Cost Estimate sheet by WBS work package; totals roll up to the Summary.
B39: 3. Enter monthly Planned Value, Earned Value and Actual Cost on Cash Flow & EVM; set the status month to obtain CPI, SPI, EAC and the S-curve.
B40: 4. Navy column headers = input columns (shaded rows are for data entry). Teal headers marked ƒ = calculated columns — do not overwrite.
B41: 5. Drop-down lists enforce the toolkit's controlled vocabulary. Rows shown in grey italics are examples — overwrite or delete them.
B42: 6. Update the Version/Status/Date above and add a Revision History row each time the workbook is re-issued.

Sheet Summary
A1: 09 — Project Budget | Budget Summary
A2: [Project Name] • PRJ-2026-001-BUD • v0.1 Draft • Internal
A4: Category | B4: Base estimate | C4: Contingency | D4: Budget | E4: Actual to date | F4: EAC | G4: Variance
A5: Labour | B5: =SUMIF('Cost Estimate'!$D$5:$D$84,$A5,'Cost Estimate'!$J$5:$J$84) -> 30600 | C5: =SUMIF('Cost Estimate'!$D$5:$D$84,$A5,'Cost Estimate'!$L$5:$L$84) -> 3060 | D5: =SUMIF('Cost Estimate'!$D$5:$D$84,$A5,'Cost Estimate'!$M$5:$M$84) -> 33660 | E5: =SUMIF('Cost Estimate'!$D$5:$D$84,$A5,'Cost Estimate'!$O$5:$O$84) -> 0 | F5: =SUMIF('Cost Estimate'!$D$5:$D$84,$A5,'Cost Estimate'!$Q$5:$Q$84) -> 0 | G5: =D5-F5 -> 33660
A6: Contractors / Services | B6: =SUMIF('Cost Estimate'!$D$5:$D$84,$A6,'Cost Estimate'!$J$5:$J$84) -> 0 | C6: =SUMIF('Cost Estimate'!$D$5:$D$84,$A6,'Cost Estimate'!$L$5:$L$84) -> 0 | D6: =SUMIF('Cost Estimate'!$D$5:$D$84,$A6,'Cost Estimate'!$M$5:$M$84) -> 0 | E6: =SUMIF('Cost Estimate'!$D$5:$D$84,$A6,'Cost Estimate'!$O$5:$O$84) -> 0 | F6: =SUMIF('Cost Estimate'!$D$5:$D$84,$A6,'Cost Estimate'!$Q$5:$Q$84) -> 0 | G6: =D6-F6 -> 0
A7: Hardware / Equipment | B7: =SUMIF('Cost Estimate'!$D$5:$D$84,$A7,'Cost Estimate'!$J$5:$J$84) -> 0 | C7: =SUMIF('Cost Estimate'!$D$5:$D$84,$A7,'Cost Estimate'!$L$5:$L$84) -> 0 | D7: =SUMIF('Cost Estimate'!$D$5:$D$84,$A7,'Cost Estimate'!$M$5:$M$84) -> 0 | E7: =SUMIF('Cost Estimate'!$D$5:$D$84,$A7,'Cost Estimate'!$O$5:$O$84) -> 0 | F7: =SUMIF('Cost Estimate'!$D$5:$D$84,$A7,'Cost Estimate'!$Q$5:$Q$84) -> 0 | G7: =D7-F7 -> 0
A8: Software / Licences | B8: =SUMIF('Cost Estimate'!$D$5:$D$84,$A8,'Cost Estimate'!$J$5:$J$84) -> 15000 | C8: =SUMIF('Cost Estimate'!$D$5:$D$84,$A8,'Cost Estimate'!$L$5:$L$84) -> 1500 | D8: =SUMIF('Cost Estimate'!$D$5:$D$84,$A8,'Cost Estimate'!$M$5:$M$84) -> 16500 | E8: =SUMIF('Cost Estimate'!$D$5:$D$84,$A8,'Cost Estimate'!$O$5:$O$84) -> 0 | F8: =SUMIF('Cost Estimate'!$D$5:$D$84,$A8,'Cost Estimate'!$Q$5:$Q$84) -> 0 | G8: =D8-F8 -> 16500
A9: Materials | B9: =SUMIF('Cost Estimate'!$D$5:$D$84,$A9,'Cost Estimate'!$J$5:$J$84) -> 0 | C9: =SUMIF('Cost Estimate'!$D$5:$D$84,$A9,'Cost Estimate'!$L$5:$L$84) -> 0 | D9: =SUMIF('Cost Estimate'!$D$5:$D$84,$A9,'Cost Estimate'!$M$5:$M$84) -> 0 | E9: =SUMIF('Cost Estimate'!$D$5:$D$84,$A9,'Cost Estimate'!$O$5:$O$84) -> 0 | F9: =SUMIF('Cost Estimate'!$D$5:$D$84,$A9,'Cost Estimate'!$Q$5:$Q$84) -> 0 | G9: =D9-F9 -> 0
A10: Travel | B10: =SUMIF('Cost Estimate'!$D$5:$D$84,$A10,'Cost Estimate'!$J$5:$J$84) -> 0 | C10: =SUMIF('Cost Estimate'!$D$5:$D$84,$A10,'Cost Estimate'!$L$5:$L$84) -> 0 | D10: =SUMIF('Cost Estimate'!$D$5:$D$84,$A10,'Cost Estimate'!$M$5:$M$84) -> 0 | E10: =SUMIF('Cost Estimate'!$D$5:$D$84,$A10,'Cost Estimate'!$O$5:$O$84) -> 0 | F10: =SUMIF('Cost Estimate'!$D$5:$D$84,$A10,'Cost Estimate'!$Q$5:$Q$84) -> 0 | G10: =D10-F10 -> 0
A11: Training | B11: =SUMIF('Cost Estimate'!$D$5:$D$84,$A11,'Cost Estimate'!$J$5:$J$84) -> 10000 | C11: =SUMIF('Cost Estimate'!$D$5:$D$84,$A11,'Cost Estimate'!$L$5:$L$84) -> 1000 | D11: =SUMIF('Cost Estimate'!$D$5:$D$84,$A11,'Cost Estimate'!$M$5:$M$84) -> 11000 | E11: =SUMIF('Cost Estimate'!$D$5:$D$84,$A11,'Cost Estimate'!$O$5:$O$84) -> 0 | F11: =SUMIF('Cost Estimate'!$D$5:$D$84,$A11,'Cost Estimate'!$Q$5:$Q$84) -> 0 | G11: =D11-F11 -> 11000
A12: Facilities | B12: =SUMIF('Cost Estimate'!$D$5:$D$84,$A12,'Cost Estimate'!$J$5:$J$84) -> 0 | C12: =SUMIF('Cost Estimate'!$D$5:$D$84,$A12,'Cost Estimate'!$L$5:$L$84) -> 0 | D12: =SUMIF('Cost Estimate'!$D$5:$D$84,$A12,'Cost Estimate'!$M$5:$M$84) -> 0 | E12: =SUMIF('Cost Estimate'!$D$5:$D$84,$A12,'Cost Estimate'!$O$5:$O$84) -> 0 | F12: =SUMIF('Cost Estimate'!$D$5:$D$84,$A12,'Cost Estimate'!$Q$5:$Q$84) -> 0 | G12: =D12-F12 -> 0
A13: Other | B13: =SUMIF('Cost Estimate'!$D$5:$D$84,$A13,'Cost Estimate'!$J$5:$J$84) -> 0 | C13: =SUMIF('Cost Estimate'!$D$5:$D$84,$A13,'Cost Estimate'!$L$5:$L$84) -> 0 | D13: =SUMIF('Cost Estimate'!$D$5:$D$84,$A13,'Cost Estimate'!$M$5:$M$84) -> 0 | E13: =SUMIF('Cost Estimate'!$D$5:$D$84,$A13,'Cost Estimate'!$O$5:$O$84) -> 0 | F13: =SUMIF('Cost Estimate'!$D$5:$D$84,$A13,'Cost Estimate'!$Q$5:$Q$84) -> 0 | G13: =D13-F13 -> 0
A14: Cost baseline (incl. contingency) | B14: =SUM(B5:B13) -> 55600 | C14: =SUM(C5:C13) -> 5560 | D14: =SUM(D5:D13) -> 61160 | E14: =SUM(E5:E13) -> 0 | F14: =SUM(F5:F13) -> 0 | G14: =SUM(G5:G13) -> 61160
A15: Management reserve | D15: =D14*Assumptions!$B$7 -> 3058
A16: TOTAL PROJECT BUDGET | D16: =D14+D15 -> 64218
A17: Uncategorized lines (check) | D17: ='Cost Estimate'!M85-D14 -> 0

Sheet Cash Flow & EVM
A1: 09 — Project Budget | Time-phased Budget, Earned Value & S-Curve
A2: [Project Name] • PRJ-2026-001-BUD • v0.1 Draft • Internal
A4: Month | B4: =DATE(2026,11,1) -> 46327 | C4: =EDATE(DATE(2026,11,1),1) -> 46357 | D4: =EDATE(DATE(2026,11,1),2) -> 46388 | E4: =EDATE(DATE(2026,11,1),3) -> 46419 | F4: =EDATE(DATE(2026,11,1),4) -> 46447 | G4: =EDATE(DATE(2026,11,1),5) -> 46478 | H4: =EDATE(DATE(2026,11,1),6) -> 46508 | I4: =EDATE(DATE(2026,11,1),7) -> 46539 | J4: =EDATE(DATE(2026,11,1),8) -> 46569 | K4: =EDATE(DATE(2026,11,1),9) -> 46600 | L4: =EDATE(DATE(2026,11,1),10) -> 46631 | M4: =EDATE(DATE(2026,11,1),11) -> 46661 | N4: Total
A5: Planned Value (PV) – monthly | N5: =SUM(B5:M5) -> 0
A6: Earned Value (EV) – monthly | N6: =SUM(B6:M6) -> 0
A7: Actual Cost (AC) – monthly | N7: =SUM(B7:M7) -> 0
A8: Cumulative PV | B8: =B5 -> 0 | C8: =SUM($B$5:C5) -> 0 | D8: =SUM($B$5:D5) -> 0 | E8: =SUM($B$5:E5) -> 0 | F8: =SUM($B$5:F5) -> 0 | G8: =SUM($B$5:G5) -> 0 | H8: =SUM($B$5:H5) -> 0 | I8: =SUM($B$5:I5) -> 0 | J8: =SUM($B$5:J5) -> 0 | ... M8: =SUM($B$5:M5) -> 0
A9: Cumulative EV | B9: =B6 -> 0 | C9: =SUM($B$6:C6) -> 0 | D9: =SUM($B$6:D6) -> 0 | E9: =SUM($B$6:E6) -> 0 | F9: =SUM($B$6:F6) -> 0 | G9: =SUM($B$6:G6) -> 0 | H9: =SUM($B$6:H6) -> 0 | I9: =SUM($B$6:I6) -> 0 | J9: =SUM($B$6:J6) -> 0 | ... M9: =SUM($B$6:M6) -> 0
A10: Cumulative AC | B10: =B7 -> 0 | C10: =SUM($B$7:C7) -> 0 | D10: =SUM($B$7:D7) -> 0 | E10: =SUM($B$7:E7) -> 0 | F10: =SUM($B$7:F7) -> 0 | G10: =SUM($B$7:G7) -> 0 | H10: =SUM($B$7:H7) -> 0 | I10: =SUM($B$7:I7) -> 0 | J10: =SUM($B$7:J7) -> 0 | ... M10: =SUM($B$7:M7) -> 0
A11: PV total vs cost baseline (should be 0) | N11: =Summary!D14-N5 -> 61160
A13: EARNED VALUE STATUS
A14: Status month (select from row 4) | B14: =B4 -> 46327
A15: BAC (cost baseline) | B15: =Summary!D14 -> 61160
A16: PV (planned value to date) | B16: =SUMPRODUCT(($B$4:$M$4<=$B$14)*($B$5:$M$5)) -> 0
A17: EV (earned value to date) | B17: =SUMPRODUCT(($B$4:$M$4<=$B$14)*($B$6:$M$6)) -> 0
A18: AC (actual cost to date) | B18: =SUMPRODUCT(($B$4:$M$4<=$B$14)*($B$7:$M$7)) -> 0
A19: CV = EV − AC | B19: =B17-B18 -> 0
A20: SV = EV − PV | B20: =B17-B16 -> 0
A21: CPI = EV / AC | B21: =IFERROR(B17/B18,"")
A22: SPI = EV / PV | B22: =IFERROR(B17/B16,"")
A23: EAC = BAC / CPI | B23: =IFERROR(B15/B21,B15) -> 61160
A24: ETC = EAC − AC | B24: =B23-B18 -> 61160
A25: VAC = BAC − EAC | B25: =B15-B23 -> 0
A26: TCPI = (BAC−EV)/(BAC−AC) | B26: =IFERROR((B15-B17)/(B15-B18),"") -> 1
A27: Cost status (RAG) | B27: =IF(B21="","",IF(B21>=0.95,"Green",IF(B21>=0.9,"Amber","Red")))
A28: Schedule status (RAG) | B28: =IF(B22="","",IF(B22>=0.95,"Green",IF(B22>=0.9,"Amber","Red")))

Sheet Assumptions
A1: 09 — Project Budget | Assumptions & Rates
A2: [Project Name] • PRJ-2026-001-BUD • v0.1 Draft • Internal
A4: Parameter | B4: Value | E4: Role / resource | F4: Rate / h (CAD)
A5: Currency | B5: CAD | E5: Project Manager | F5: 120
A6: Contingency reserve % (default) | B6: 0.1 | E6: Business Analyst | F6: 95
A7: Management reserve % of cost baseline | B7: 0.05 | E7: Technical Lead | F7: 130
A8: Hours per working day | B8: 8 | E8: Developer / Engineer | F8: 105
A9: Estimate class | B9: Definitive (-5% / +10%) | E9: QA / Tester | F9: 85
E10: Change / Training Lead | F10: 90
E11: Subject-Matter Expert | F11: 80
E12: [Role] | F12: 0

Sheet Cost Estimate
A1: 09 — Project Budget | Cost Estimate
A2: [Project Name] • PRJ-2026-001-BUD • v0.1 Draft • Internal
A4: WBS ID | B4: Control account | C4: Cost item / description | D4: Category | E4: Role (labour only) | F4: Qty / hours | G4: Unit | H4: Unit rate (CAD) | I4: ƒ Rate used | J4: ƒ Base estimate | K4: Contingency % | L4: ƒ Contingency | M4: ƒ Budget (BAC line) | N4: Committed (PO) | O4: Actual to date | P4: ETC | Q4: ƒ EAC | R4: ƒ Variance (BAC-EAC) | S4: ƒ Var. %
A5: 1.1.2 | B5: CA-1100 | C5: Project management – planning phase | D5: Labour | E5: Project Manager | F5: 160 | G5: h | I5: =IF(H5<>"",H5,IF(E5<>"",IFERROR(VLOOKUP(E5,Assumptions!$E$5:$F$12,2,FALSE()),0),0)) -> 120 | J5: =IF(F5="","",F5*I5) -> 19200 | L5: =IF(J5="","",J5*IF(K5="",Assumptions!$B$6,K5)) -> 1920 | M5: =IF(J5="","",J5+L5) -> 21120 | Q5: =IF(AND(O5="",P5=""),"",N(O5)+N(P5)) | R5: =IF(OR(M5="",Q5=""),"",M5-Q5) | S5: =IF(OR(R5="",N(M5)=0),"",R5/M5)
A6: 1.2.1 | B6: CA-1200 | C6: Current-state assessment | D6: Labour | E6: Business Analyst | F6: 120 | G6: h | I6: =IF(H6<>"",H6,IF(E6<>"",IFERROR(VLOOKUP(E6,Assumptions!$E$5:$F$12,2,FALSE()),0),0)) -> 95 | J6: =IF(F6="","",F6*I6) -> 11400 | L6: =IF(J6="","",J6*IF(K6="",Assumptions!$B$6,K6)) -> 1140 | M6: =IF(J6="","",J6+L6) -> 12540 | Q6: =IF(AND(O6="",P6=""),"",N(O6)+N(P6)) | R6: =IF(OR(M6="",Q6=""),"",M6-Q6) | S6: =IF(OR(R6="",N(M6)=0),"",R6/M6)
A7: 1.4.1 | B7: CA-1400 | C7: Software licences – year 1 | D7: Software / Licences | F7: 25 | G7: user | H7: 600 | I7: =IF(H7<>"",H7,IF(E7<>"",IFERROR(VLOOKUP(E7,Assumptions!$E$5:$F$12,2,FALSE()),0),0)) -> 600 | J7: =IF(F7="","",F7*I7) -> 15000 | L7: =IF(J7="","",J7*IF(K7="",Assumptions!$B$6,K7)) -> 1500 | M7: =IF(J7="","",J7+L7) -> 16500 | Q7: =IF(AND(O7="",P7=""),"",N(O7)+N(P7)) | R7: =IF(OR(M7="",Q7=""),"",M7-Q7) | S7: =IF(OR(R7="",N(M7)=0),"",R7/M7)
A8: 1.6.1 | B8: CA-1600 | C8: End-user training delivery | D8: Training | F8: 4 | G8: session | H8: 2500 | I8: =IF(H8<>"",H8,IF(E8<>"",IFERROR(VLOOKUP(E8,Assumptions!$E$5:$F$12,2,FALSE()),0),0)) -> 2500 | J8: =IF(F8="","",F8*I8) -> 10000 | L8: =IF(J8="","",J8*IF(K8="",Assumptions!$B$6,K8)) -> 1000 | M8: =IF(J8="","",J8+L8) -> 11000 | Q8: =IF(AND(O8="",P8=""),"",N(O8)+N(P8)) | R8: =IF(OR(M8="",Q8=""),"",M8-Q8) | S8: =IF(OR(R8="",N(M8)=0),"",R8/M8)
I9: =IF(H9<>"",H9,IF(E9<>"",IFERROR(VLOOKUP(E9,Assumptions!$E$5:$F$12,2,FALSE()),0),0)) -> 0 | J9: =IF(F9="","",F9*I9) | L9: =IF(J9="","",J9*IF(K9="",Assumptions!$B$6,K9)) | M9: =IF(J9="","",J9+L9) | Q9: =IF(AND(O9="",P9=""),"",N(O9)+N(P9)) | R9: =IF(OR(M9="",Q9=""),"",M9-Q9) | S9: =IF(OR(R9="",N(M9)=0),"",R9/M9)
I10: =IF(H10<>"",H10,IF(E10<>"",IFERROR(VLOOKUP(E10,Assumptions!$E$5:$F$12,2,FALSE()),0),0)) -> 0 | J10: =IF(F10="","",F10*I10) | L10: =IF(J10="","",J10*IF(K10="",Assumptions!$B$6,K10)) | M10: =IF(J10="","",J10+L10) | Q10: =IF(AND(O10="",P10=""),"",N(O10)+N(P10)) | R10: =IF(OR(M10="",Q10=""),"",M10-Q10) | S10: =IF(OR(R10="",N(M10)=0),"",R10/M10)
I11: =IF(H11<>"",H11,IF(E11<>"",IFERROR(VLOOKUP(E11,Assumptions!$E$5:$F$12,2,FALSE()),0),0)) -> 0 | J11: =IF(F11="","",F11*I11) | L11: =IF(J11="","",J11*IF(K11="",Assumptions!$B$6,K11)) | M11: =IF(J11="","",J11+L11) | Q11: =IF(AND(O11="",P11=""),"",N(O11)+N(P11)) | R11: =IF(OR(M11="",Q11=""),"",M11-Q11) | S11: =IF(OR(R11="",N(M11)=0),"",R11/M11)
I12: =IF(H12<>"",H12,IF(E12<>"",IFERROR(VLOOKUP(E12,Assumptions!$E$5:$F$12,2,FALSE()),0),0)) -> 0 | J12: =IF(F12="","",F12*I12) | L12: =IF(J12="","",J12*IF(K12="",Assumptions!$B$6,K12)) | M12: =IF(J12="","",J12+L12) | Q12: =IF(AND(O12="",P12=""),"",N(O12)+N(P12)) | R12: =IF(OR(M12="",Q12=""),"",M12-Q12) | S12: =IF(OR(R12="",N(M12)=0),"",R12/M12)
I13: =IF(H13<>"",H13,IF(E13<>"",IFERROR(VLOOKUP(E13,Assumptions!$E$5:$F$12,2,FALSE()),0),0)) -> 0 | J13: =IF(F13="","",F13*I13) | L13: =IF(J13="","",J13*IF(K13="",Assumptions!$B$6,K13)) | M13: =IF(J13="","",J13+L13) | Q13: =IF(AND(O13="",P13=""),"",N(O13)+N(P13)) | R13: =IF(OR(M13="",Q13=""),"",M13-Q13) | S13: =IF(OR(R13="",N(M13)=0),"",R13/M13)
I14: =IF(H14<>"",H14,IF(E14<>"",IFERROR(VLOOKUP(E14,Assumptions!$E$5:$F$12,2,FALSE()),0),0)) -> 0 | J14: =IF(F14="","",F14*I14) | L14: =IF(J14="","",J14*IF(K14="",Assumptions!$B$6,K14)) | M14: =IF(J14="","",J14+L14) | Q14: =IF(AND(O14="",P14=""),"",N(O14)+N(P14)) | R14: =IF(OR(M14="",Q14=""),"",M14-Q14) | S14: =IF(OR(R14="",N(M14)=0),"",R14/M14)
I15: =IF(H15<>"",H15,IF(E15<>"",IFERROR(VLOOKUP(E15,Assumptions!$E$5:$F$12,2,FALSE()),0),0)) -> 0 | J15: =IF(F15="","",F15*I15) | L15: =IF(J15="","",J15*IF(K15="",Assumptions!$B$6,K15)) | M15: =IF(J15="","",J15+L15) | Q15: =IF(AND(O15="",P15=""),"",N(O15)+N(P15)) | R15: =IF(OR(M15="",Q15=""),"",M15-Q15) | S15: =IF(OR(R15="",N(M15)=0),"",R15/M15)
I16: =IF(H16<>"",H16,IF(E16<>"",IFERROR(VLOOKUP(E16,Assumptions!$E$5:$F$12,2,FALSE()),0),0)) -> 0 | J16: =IF(F16="","",F16*I16) | L16: =IF(J16="","",J16*IF(K16="",Assumptions!$B$6,K16)) | M16: =IF(J16="","",J16+L16) | Q16: =IF(AND(O16="",P16=""),"",N(O16)+N(P16)) | R16: =IF(OR(M16="",Q16=""),"",M16-Q16) | S16: =IF(OR(R16="",N(M16)=0),"",R16/M16)
I17: =IF(H17<>"",H17,IF(E17<>"",IFERROR(VLOOKUP(E17,Assumptions!$E$5:$F$12,2,FALSE()),0),0)) -> 0 | J17: =IF(F17="","",F17*I17) | L17: =IF(J17="","",J17*IF(K17="",Assumptions!$B$6,K17)) | M17: =IF(J17="","",J17+L17) | Q17: =IF(AND(O17="",P17=""),"",N(O17)+N(P17)) | R17: =IF(OR(M17="",Q17=""),"",M17-Q17) | S17: =IF(OR(R17="",N(M17)=0),"",R17/M17)
I18: =IF(H18<>"",H18,IF(E18<>"",IFERROR(VLOOKUP(E18,Assumptions!$E$5:$F$12,2,FALSE()),0),0)) -> 0 | J18: =IF(F18="","",F18*I18) | L18: =IF(J18="","",J18*IF(K18="",Assumptions!$B$6,K18)) | M18: =IF(J18="","",J18+L18) | Q18: =IF(AND(O18="",P18=""),"",N(O18)+N(P18)) | R18: =IF(OR(M18="",Q18=""),"",M18-Q18) | S18: =IF(OR(R18="",N(M18)=0),"",R18/M18)
I19: =IF(H19<>"",H19,IF(E19<>"",IFERROR(VLOOKUP(E19,Assumptions!$E$5:$F$12,2,FALSE()),0),0)) -> 0 | J19: =IF(F19="","",F19*I19) | L19: =IF(J19="","",J19*IF(K19="",Assumptions!$B$6,K19)) | M19: =IF(J19="","",J19+L19) | Q19: =IF(AND(O19="",P19=""),"",N(O19)+N(P19)) | R19: =IF(OR(M19="",Q19=""),"",M19-Q19) | S19: =IF(OR(R19="",N(M19)=0),"",R19/M19)
I20: =IF(H20<>"",H20,IF(E20<>"",IFERROR(VLOOKUP(E20,Assumptions!$E$5:$F$12,2,FALSE()),0),0)) -> 0 | J20: =IF(F20="","",F20*I20) | L20: =IF(J20="","",J20*IF(K20="",Assumptions!$B$6,K20)) | M20: =IF(J20="","",J20+L20) | Q20: =IF(AND(O20="",P20=""),"",N(O20)+N(P20)) | R20: =IF(OR(M20="",Q20=""),"",M20-Q20) | S20: =IF(OR(R20="",N(M20)=0),"",R20/M20)
... I84: =IF(H84<>"",H84,IF(E84<>"",IFERROR(VLOOKUP(E84,Assumptions!$E$5:$F$12,2,FALSE()),0),0)) -> 0 | J84: =IF(F84="","",F84*I84) | L84: =IF(J84="","",J84*IF(K84="",Assumptions!$B$6,K84)) | M84: =IF(J84="","",J84+L84) | Q84: =IF(AND(O84="",P84=""),"",N(O84)+N(P84)) | R84: =IF(OR(M84="",Q84=""),"",M84-Q84) | S84: =IF(OR(R84="",N(M84)=0),"",R84/M84)
C85: TOTAL | J85: =SUM(J5:J84) -> 55600 | L85: =SUM(L5:L84) -> 5560 | M85: =SUM(M5:M84) -> 61160 | N85: =SUM(N5:N84) -> 0 | O85: =SUM(O5:O84) -> 0 | P85: =SUM(P5:P84) -> 0 | Q85: =SUM(Q5:Q84) -> 0 | R85: =SUM(R5:R84) -> 0

Sheet Lists
A1: CostCat | B1: Roles
A2: Labour | B2: Project Manager
A3: Contractors / Services | B3: Business Analyst
A4: Hardware / Equipment | B4: Technical Lead
A5: Software / Licences | B5: Developer / Engineer
A6: Materials | B6: QA / Tester
A7: Travel | B7: Change / Training Lead
A8: Training | B8: Subject-Matter Expert
A9: Facilities | B9: [Role]
A10: Other
